Workbook

Sheet Supuestos
A1: Supuestos y fuentes — Lemmatica (SaaS de documentación clínica)
A2: Verificado = confirmado hoy contra la fuente citada. Supuesto = estimación/palanca editable — ajústala a tu realidad.
A4: Parámetro | B4: Valor | C4: Unidad | D4: Tipo | E4: Fuente
A5: Gemini 2.5 Pro — input (prompt ≤200k tokens) | B5: 1.25 | C5: $/1M tokens | D5: Verificado | E5: ai.google.dev/gemini-api/docs/pricing (20-ago-2026)
A6: Gemini 2.5 Pro — output (prompt ≤200k tokens) | B6: 10 | C6: $/1M tokens | D6: Verificado | E6: ai.google.dev/gemini-api/docs/pricing (20-ago-2026)
A7: Gemini 2.5 Flash — input texto | B7: 0.3 | C7: $/1M tokens | D7: Verificado | E7: ai.google.dev/gemini-api/docs/pricing (20-ago-2026)
A8: Gemini 2.5 Flash — output | B8: 2.5 | C8: $/1M tokens | D8: Verificado | E8: ai.google.dev/gemini-api/docs/pricing (20-ago-2026)
A9: Gemini 2.5 Flash — input audio | B9: 1 | C9: $/1M tokens | D9: Verificado | E9: ai.google.dev/gemini-api/docs/pricing (20-ago-2026)
A10: Tasa de tokenización de audio (confirmada en Flash; NO listada por separado para 2.5 Pro — VERIFICAR antes de cotizar) | B10: 25 | C10: tokens/segundo | D10: Verificado (Flash) / asumido en Pro | E10: ai.google.dev/gemini-api/docs/pricing (20-ago-2026)
A11: AssemblyAI Universal-2 (STT, 99 idiomas incl. español) | B11: 0.15 | C11: $/hora audio | D11: Verificado | E11: assemblyai.com/pricing (20-ago-2026)
A12: Deepgram Nova-3 Multilingüe (STT streaming) | B12: 0.0058 | C12: $/minuto audio | D12: Verificado — confirmar cobertura es-MX explícita | E12: deepgram.com/pricing (20-ago-2026)
A13: Duración promedio de consulta | B13: 15 | C13: minutos | D13: Supuesto (palanca) | E13: Estimación de negocio — ajustar con datos reales
A14: Palabras por minuto de habla clínica es-MX | B14: 130 | C14: palabras/min | D14: Supuesto (palanca) | E14: Estimación de habla conversacional — ajustar
A15: Tokens por palabra en español (aprox.) | B15: 1.3 | C15: tokens/palabra | D15: Supuesto | E15: Regla general de tokenizadores en español
A16: Tokens de salida por consulta (SOAP + tratamientos + indicaciones) | B16: 2500 | C16: tokens | D16: Supuesto (palanca) | E16: Estimado del prompt en aiTranscriptionService.js
... A30: IVA México | B30: 0.16 | C30: fracción | D30: Supuesto (conocido) | E30: Ley del IVA

Sheet CostoConsulta
A1: Costo de IA por consulta — 3 escenarios de arquitectura
A2: Todas las celdas de esta hoja son fórmulas que jalan de 'Supuestos'. Cambia los supuestos ahí, no aquí.
A4: Escenario | B4: Minutos | C4: Costo STT ($) | D4: Tokens entrada | E4: Costo entrada LLM ($) | F4: Tokens salida | G4: Costo salida LLM ($) | H4: Costo total/consulta ($) | I4: Nota
A5: Actual: Web Speech API (navegador) + Gemini texto | B5: =Supuestos!$B$13 -> 15 | C5: 0 | D5: =B5*Supuestos!$B$14*Supuestos!$B$15 -> 2535 | E5: =D5/1000000*Supuestos!$B$5 -> 0.00316875 | F5: =Supuestos!$B$16 -> 2500 | G5: =F5/1000000*Supuestos!$B$6 -> 0.025 | H5: =C5+E5+G5 -> 0.02816875 | I5: Riesgo LEGAL, no económico: el audio se envía a los servidores de Google vía el navegador, fuera de cualquier contrato de datos. Ver informe técnico.
A6: Recomendado: STT dedicado (AssemblyAI) + Gemini texto | B6: =Supuestos!$B$13 -> 15 | C6: =(B6/60)*Supuestos!$B$11 -> 0.0375 | D6: =B6*Supuestos!$B$14*Supuestos!$B$15 -> 2535 | E6: =D6/1000000*Supuestos!$B$5 -> 0.00316875 | F6: =Supuestos!$B$16 -> 2500 | G6: =F6/1000000*Supuestos!$B$6 -> 0.025 | H6: =C6+E6+G6 -> 0.06566875 | I6: STT con proveedor bajo contrato + Gemini solo para estructurar texto. Costo total más alto que el actual pero con cobertura legal.
A7: Multimodal nativo: audio directo a Gemini 2.5 Pro (sin STT aparte) | B7: =Supuestos!$B$13 -> 15 | C7: 0 | D7: =B7*60*Supuestos!$B$10 -> 22500 | E7: =D7/1000000*Supuestos!$B$5 -> 0.028125 | F7: =Supuestos!$B$16 -> 2500 | G7: =F7/1000000*Supuestos!$B$6 -> 0.025 | H7: =C7+E7+G7 -> 0.053125 | I7: Asume que Gemini 2.5 Pro factura audio a la tarifa de texto de entrada (no confirmado en la página de precios para este modelo específico) — VERIFICAR antes de usar para cotizar.
A9: El resto del modelo usa el escenario 'Recomendado' (fila 6) como costo variable de IA por consulta.

Sheet CostoMedicoMes
A1: Costo por médico al mes, por nivel de uso
A2: Doctores activos usados para prorratear el hosting fijo (ajusta esta palanca): | F2: 30
A4: Nivel de uso | B4: Consultas/mes | C4: MB audio/consulta | D4: GB audio/mes | E4: Costo almacenamiento ($) | F4: Costo variable IA ($) | G4: Hosting fijo total ($) | H4: Hosting amortizado/médico ($) | I4: COGS total/médico/mes ($)
A5: Ligero | B5: 20 | C5: =(Supuestos!$B$17*Supuestos!$B$13*60/8)/1024 -> 3.515625 | D5: =B5*C5/1024 -> 0.068664551 | E5: =D5*Supuestos!$B$18 -> 0.0010299683 | F5: =B5*CostoConsulta!$H$6 -> 1.313375 | G5: =Supuestos!$B$21+Supuestos!$B$22+Supuestos!$B$23+Supuestos!$B$24 -> 85 | H5: =G5/$F$2 -> 2.8333333 | I5: =E5+F5+H5 -> 4.1477383
A6: Medio | B6: 80 | C6: =(Supuestos!$B$17*Supuestos!$B$13*60/8)/1024 -> 3.515625 | D6: =B6*C6/1024 -> 0.2746582 | E6: =D6*Supuestos!$B$18 -> 0.004119873 | F6: =B6*CostoConsulta!$H$6 -> 5.2535 | G6: =Supuestos!$B$21+Supuestos!$B$22+Supuestos!$B$23+Supuestos!$B$24 -> 85 | H6: =G6/$F$2 -> 2.8333333 | I6: =E6+F6+H6 -> 8.0909532
A7: Intensivo | B7: 200 | C7: =(Supuestos!$B$17*Supuestos!$B$13*60/8)/1024 -> 3.515625 | D7: =B7*C7/1024 -> 0.68664551 | E7: =D7*Supuestos!$B$18 -> 0.010299683 | F7: =B7*CostoConsulta!$H$6 -> 13.13375 | G7: =Supuestos!$B$21+Supuestos!$B$22+Supuestos!$B$23+Supuestos!$B$24 -> 85 | H7: =G7/$F$2 -> 2.8333333 | I7: =E7+F7+H7 -> 15.977383
A9: Nota: incluso en uso intensivo, el almacenamiento de audio comprimido en R2 cuesta centavos. El problema del audio en base64 dentro de Postgres (ver informe técnico) es de arquitectura/rendimiento, no de costo por GB.

Sheet PreciosMargen
A1: Planes de precio propuestos vs. margen bruto
A3: Plan | B3: Precio (USD/mes) | C3: Precio aprox. (MXN+IVA/mes) | D3: Uso asumido | E3: COGS asociado ($) | F3: Margen bruto ($) | G3: Margen bruto (%) | H3: Nota
A4: Starter (individual) | B4: 30 | C4: =B4*Supuestos!$B$25*(1+Supuestos!$B$30) -> 643.8 | D4: Ligero | E4: =CostoMedicoMes!$I$5 -> 4.1477383 | F4: =B4-E4 -> 25.852262 | G4: =F4/B4 -> 0.86174206 | H4: Ancla frente a Noa Notes (~$550 MXN+IVA ≈ $30 USD/mes) — mismo rango de precio, más funciones (expediente, agenda).
A5: Pro (individual, uso alto) | B5: 45 | C5: =B5*Supuestos!$B$25*(1+Supuestos!$B$30) -> 965.7 | D5: Medio | E5: =CostoMedicoMes!$I$6 -> 8.0909532 | F5: =B5-E5 -> 36.909047 | G5: =F5/B5 -> 0.82020104 | H5: Entre Noa Notes y el paquete completo de Doctoralia; por debajo de Freed.ai Core ($79 USD).
A6: Clínica (con asistente) | B6: 75 | C6: =B6*Supuestos!$B$25*(1+Supuestos!$B$30) -> 1609.5 | D6: Intensivo | E6: =CostoMedicoMes!$I$7 -> 15.977383 | F6: =B6-E6 -> 59.022617 | G6: =F6/B6 -> 0.78696823 | H6: Para consultorios con 1+ asistente; compite con el paquete Plus de Doctoralia ($2,340 MXN+IVA) pero sin marketplace de pacientes.
A8: El margen bruto real depende de cuánto uso realmente hace cada médico dentro de su plan — estos supuestos son un punto de partida, no una promesa.

Sheet PuntoEquilibrio
A1: Punto de equilibrio — médicos pagantes necesarios
A2: Costos fijos operativos adicionales (soporte, ventas, nómina — NO infraestructura, esa ya está en 'Supuestos'): | E2: 0 | F2: $/mes — AJUSTA a tu estructura real
A4: Plan | B4: Precio ($) | C4: COGS/médico ($) | D4: Margen de contribución ($) | E4: Costos fijos totales ($) | F4: Médicos necesarios (breakeven)
A5: =PreciosMargen!A4 -> Starter (individual) | B5: =PreciosMargen!B4 -> 30 | C5: =PreciosMargen!E4 -> 4.1477383 | D5: =B5-C5 -> 25.852262 | E5: =(Supuestos!$B$21+Supuestos!$B$22+Supuestos!$B$23+Supuestos!$B$24)+$E$2 -> 85 | F5: =IF(D5<=0,"n/a (margen negativo)",ROUNDUP(E5/D5,0)) -> 4
A6: =PreciosMargen!A5 -> Pro (individual, uso alto) | B6: =PreciosMargen!B5 -> 45 | C6: =PreciosMargen!E5 -> 8.0909532 | D6: =B6-C6 -> 36.909047 | E6: =(Supuestos!$B$21+Supuestos!$B$22+Supuestos!$B$23+Supuestos!$B$24)+$E$2 -> 85 | F6: =IF(D6<=0,"n/a (margen negativo)",ROUNDUP(E6/D6,0)) -> 3
A7: =PreciosMargen!A6 -> Clínica (con asistente) | B7: =PreciosMargen!B6 -> 75 | C7: =PreciosMargen!E6 -> 15.977383 | D7: =B7-C7 -> 59.022617 | E7: =(Supuestos!$B$21+Supuestos!$B$22+Supuestos!$B$23+Supuestos!$B$24)+$E$2 -> 85 | F7: =IF(D7<=0,"n/a (margen negativo)",ROUNDUP(E7/D7,0)) -> 2
A9: Con costos fijos en $0 (solo infraestructura), 3-5 médicos pagantes en cualquier plan cubren el hosting. Todo lo que venga después es margen de contribución hacia adquisición, soporte y equipo.

Sheet CAC_LTV
A1: CAC / LTV — estimación inicial (plan Pro como referencia)
A3: Parámetro | B3: Valor | C3: Fuente / nota
A4: ARPU mensual ($) | B4: =PreciosMargen!B5 -> 45 | C4: Precio del plan Pro
A5: Margen bruto (%) | B5: =PreciosMargen!G5 -> 0.82020104 | C5: Del plan Pro
A6: Churn mensual asumido | B6: 0.04 | C6: Referencia genérica de SaaS SMB — NO verificado para este mercado. AJUSTAR con datos reales en cuanto existan.
A7: Vida promedio del cliente (meses) | B7: =1/B6 -> 25 | C7: Fórmula: 1 / churn mensual
A8: LTV ($) | B8: =B4*B5/B6 -> 922.72617 | C8: Fórmula: ARPU × margen bruto / churn
A9: CAC asumido ($) | B9: 40 | C9: Estimación inicial, sin datos de adquisición reales aún. AJUSTAR en cuanto corras tus primeras campañas/ventas.
A10: Relación LTV:CAC | B10: =B8/B9 -> 23.068154 | C10: Regla general SaaS: sano si es ≥ 3
A11: Periodo de recuperación de CAC (meses) | B11: =B9/(B4*B5) -> 1.0837451 | C11: Fórmula: CAC / (ARPU × margen bruto)
A13: Estos dos supuestos (churn y CAC) son los que más mueven la conclusión y los que menos evidencia real tienen hoy. Prioriza medirlos apenas tengas tus primeros 10-20 clientes.

Sheet Mercado
A1: Tamaño de mercado — TAM / SAM / SOM (México)
A2: AVISO: las cifras de este bloque NO se verificaron en vivo — la búsqueda web falló durante toda esta sesión. Son referencias de memoria + supuestos de trabajo. Confirma densidad de médicos y población con INEGI/OCDE (oecd.org/health) y cifras de médicos activos con fuentes públicas de Doctoralia antes de usar esto en un pitch o plan formal.
A5: Concepto | B5: Valor | C5: Unidad | D5: Nota
A6: Densidad de médicos en México (referencia histórica OCDE) | B6: 2.4 | C6: médicos por 1,000 hab. | D6: NO VERIFICADO HOY — confirmar en oecd.org/health antes de usar
A7: Población de México (referencia) | B7: 130 | C7: millones | D7: NO VERIFICADO HOY — confirmar con INEGI/Banco Mundial
A8: Médicos en ejercicio, estimado | B8: =B6*B7*1000 -> 312000 | C8: médicos | D8: Fórmula: densidad × población × 1,000
A9: % con consultorio propio / práctica privada (incl. quienes combinan con sector público) | B9: 0.5 | C9: fracción | D9: Supuesto de trabajo — NO VERIFICADO
A10: TAM — médicos independientes con consultorio (estimado) | B10: =B8*B9 -> 156000 | C10: médicos | D10: Fórmula: médicos en ejercicio × % con consultorio propio
A11: % SAM (especialidades tipo consulta 1:1, cómodas con software, con internet) | B11: 0.55 | C11: fracción | D11: Supuesto de trabajo — ajustar
A12: SAM estimado | B12: =B10*B11 -> 85800 | C12: médicos | D12: Fórmula: TAM × % SAM
A13: % SOM objetivo a 24-36 meses (penetración realista, etapa temprana) | B13: 0.01 | C13: fracción | D13: Supuesto de trabajo — ajustar según capacidad de ventas
A14: SOM estimado (médicos pagantes) | B14: =B12*B13 -> 858 | C14: médicos | D14: Fórmula: SAM × % SOM
A15: ARR potencial en SOM (usando ARPU del plan Pro) | B15: =B14*PreciosMargen!B5*12 -> 463320 | C15: $/año | D15: Fórmula: SOM × precio Pro × 12 — puramente ilustrativo
A17: Trata estos números como un orden de magnitud para conversación interna, no como un dato para un inversionista hasta que verifiques la fuente.

Sheet Fuentes
A1: Fuentes consultadas (20 de agosto, 2026)
A3: Fecha | B3: Fuente | C3: URL | D3: Dato obtenido
A4: 2026-08-20 | B4: Google AI for Developers | C4: https://ai.google.dev/gemini-api/docs/pricing | D4: Precios Gemini 2.5 Pro / 2.5 Flash, tokenización de audio (25 tok/seg en Flash)
A5: 2026-08-20 | B5: Supabase | C5: https://supabase.com/pricing | D5: Planes Free / Pro / Team, límites de base de datos y bandwidth
A6: 2026-08-20 | B6: Cloudflare | C6: https://developers.cloudflare.com/r2/pricing/ | D6: R2: storage $0.015/GB-mes, egreso directo gratuito
A7: 2026-08-20 | B7: Railway | C7: https://railway.com/pricing | D7: Planes Hobby ($5) / Pro ($20), precio por vCPU/RAM
A8: 2026-08-20 | B8: Render | C8: https://render.com/pricing | D8: Starter ($7) / Standard ($25) para backend Node.js
A9: 2026-08-20 | B9: Vercel | C9: https://vercel.com/pricing | D9: Hobby (gratis) / Pro ($20) para frontend
A10: 2026-08-20 | B10: AssemblyAI | C10: https://www.assemblyai.com/pricing | D10: STT Universal-2 $0.15/hora (99 idiomas, incl. español)
A11: 2026-08-20 | B11: Deepgram | C11: https://deepgram.com/pricing | D11: STT Nova-3 Multilingüe $0.0058/min (streaming)
A12: 2026-08-20 | B12: OpenAI | C12: https://openai.com/api/pricing/ | D12: Modelos GPT-5.6, GPT-Live-Transcribe $0.017/min
A13: 2026-08-20 | B13: Doctoralia PRO México | C13: https://pro.doctoralia.com.mx/precios/medicos-y-especialistas | D13: Planes Starter/Plus/VIP ($1,740-$2,970 MXN+IVA) y Noa Notes add-on ($550 MXN+IVA)
A14: 2026-08-20 | B14: Freed.ai | C14: https://www.getfreed.ai/pricing | D14: Planes Starter ($39) / Core ($79) / Premier ($104-119 USD)
A16: Heidi Health, Nabla y Suki no mostraron precios públicos verificables hoy (páginas dinámicas sin tabla de precios, o 404). Suki es venta enterprise ('contact us').
A17: La herramienta de búsqueda web (WebSearch) rechazó todas las solicitudes durante esta sesión (error de proxy). El número de médicos en México, la población y el tipo de cambio NO pudieron verificarse en vivo — quedan marcados como 'NO VERIFICADO' en las hojas 'Supuestos' y 'Mercado'.
